Gempyre/__init__.py
Gempyre/_gempyre.cp38-win_amd64.pyd
Gempyre/resource.py
Gempyre/cmake/LibwebsocketsTargets-release.cmake
Gempyre/cmake/LibwebsocketsTargets.cmake
Gempyre/cmake/LwsCheckRequirements.cmake
Gempyre/cmake/libwebsockets-config-version.cmake
Gempyre/cmake/libwebsockets-config.cmake
Gempyre/include/libwebsockets.h
Gempyre/include/lws_config.h
Gempyre/include/libwebsockets/lws-adopt.h
Gempyre/include/libwebsockets/lws-async-dns.h
Gempyre/include/libwebsockets/lws-bb-i2c.h
Gempyre/include/libwebsockets/lws-bb-spi.h
Gempyre/include/libwebsockets/lws-button.h
Gempyre/include/libwebsockets/lws-cache-ttl.h
Gempyre/include/libwebsockets/lws-callbacks.h
Gempyre/include/libwebsockets/lws-cgi.h
Gempyre/include/libwebsockets/lws-client.h
Gempyre/include/libwebsockets/lws-conmon.h
Gempyre/include/libwebsockets/lws-context-vhost.h
Gempyre/include/libwebsockets/lws-cose.h
Gempyre/include/libwebsockets/lws-dbus.h
Gempyre/include/libwebsockets/lws-diskcache.h
Gempyre/include/libwebsockets/lws-display.h
Gempyre/include/libwebsockets/lws-dll2.h
Gempyre/include/libwebsockets/lws-dsh.h
Gempyre/include/libwebsockets/lws-eventlib-exports.h
Gempyre/include/libwebsockets/lws-fault-injection.h
Gempyre/include/libwebsockets/lws-freertos.h
Gempyre/include/libwebsockets/lws-fts.h
Gempyre/include/libwebsockets/lws-genaes.h
Gempyre/include/libwebsockets/lws-gencrypto.h
Gempyre/include/libwebsockets/lws-genec.h
Gempyre/include/libwebsockets/lws-genhash.h
Gempyre/include/libwebsockets/lws-genrsa.h
Gempyre/include/libwebsockets/lws-gpio.h
Gempyre/include/libwebsockets/lws-http.h
Gempyre/include/libwebsockets/lws-i2c.h
Gempyre/include/libwebsockets/lws-ili9341-spi.h
Gempyre/include/libwebsockets/lws-jose.h
Gempyre/include/libwebsockets/lws-jwe.h
Gempyre/include/libwebsockets/lws-jwk.h
Gempyre/include/libwebsockets/lws-jws.h
Gempyre/include/libwebsockets/lws-lecp.h
Gempyre/include/libwebsockets/lws-led.h
Gempyre/include/libwebsockets/lws-lejp.h
Gempyre/include/libwebsockets/lws-logs.h
gempyre-1.8.2.dist-info/LICENSE.txt
gempyre-1.8.2.dist-info/METADATA
gempyre-1.8.2.dist-info/WHEEL
gempyre-1.8.2.dist-info/top_level.txt
gempyre-1.8.2.dist-info/RECORD
