Metadata-Version: 2.1
Name: Gempyre
Version: 1.8.2
Summary: Gempyre is a framework for quick and simple UI development
Author-email: Markus Mertama <author99@example.com>
Project-URL: Homepage, https://github.com/mmertama
Classifier: Programming Language :: Python :: 3
Classifier: Topic :: Software Development :: User Interfaces
Classifier: License :: OSI Approved :: MIT License
Classifier: Operating System :: POSIX :: Linux
Classifier: Operating System :: MacOS
Classifier: Operating System :: Microsoft :: Windows
Requires-Python: >=3.8
License-File: LICENSE.txt
Requires-Dist: websockets
